redis_log_handler/__init__.py
redis_log_handler-0.0.1.dev32.dist-info/AUTHORS
redis_log_handler-0.0.1.dev32.dist-info/LICENSE
redis_log_handler-0.0.1.dev32.dist-info/METADATA
redis_log_handler-0.0.1.dev32.dist-info/WHEEL
redis_log_handler-0.0.1.dev32.dist-info/pbr.json
redis_log_handler-0.0.1.dev32.dist-info/top_level.txt
redis_log_handler-0.0.1.dev32.dist-info/RECORD
