Metadata-Version: 2.1
Name: redis-log-handler
Version: 0.0.1.dev32
Summary: A log handler for the Python logging module, emitting all logs to specific Redis channels
Home-page: https://gitlab.adimian.com/open-source/redis-log-handler
Author: See AUTHORS
Author-email: contact@adimian.com
License: UNKNOWN
Platform: UNKNOWN
Classifier: Development Status :: 4 - Beta
Classifier: Operating System :: POSIX
Classifier: License :: OSI Approved :: MIT License
Classifier: Programming Language :: Python
Classifier: Programming Language :: Python :: 3.6
Classifier: Programming Language :: Python :: 3.7
Requires-Dist: redis (==3.0.1)
